goose3/__init__.py
goose3/article.py
goose3/cleaners.py
goose3/configuration.py
goose3/crawler.py
goose3/exceptions.py
goose3/image.py
goose3/network.py
goose3/outputformatters.py
goose3/parsers.py
goose3/text.py
goose3/version.py
goose3/video.py
goose3/extractors/__init__.py
goose3/extractors/authors.py
goose3/extractors/content.py
goose3/extractors/images.py
goose3/extractors/links.py
goose3/extractors/metas.py
goose3/extractors/opengraph.py
goose3/extractors/publishdate.py
goose3/extractors/schema.py
goose3/extractors/tags.py
goose3/extractors/title.py
goose3/extractors/tweets.py
goose3/extractors/videos.py
goose3/resources/images/known-image-css.txt
goose3/resources/text/stopwords-ar.txt
goose3/resources/text/stopwords-be.txt
goose3/resources/text/stopwords-bg.txt
goose3/resources/text/stopwords-da.txt
goose3/resources/text/stopwords-de.txt
goose3/resources/text/stopwords-el.txt
goose3/resources/text/stopwords-en.txt
goose3/resources/text/stopwords-es.txt
goose3/resources/text/stopwords-et.txt
goose3/resources/text/stopwords-fa.txt
goose3/resources/text/stopwords-fi.txt
goose3/resources/text/stopwords-fr.txt
goose3/resources/text/stopwords-he.txt
goose3/resources/text/stopwords-hi.txt
goose3/resources/text/stopwords-hr.txt
goose3/resources/text/stopwords-hu.txt
goose3/resources/text/stopwords-hy.txt
goose3/resources/text/stopwords-id.txt
goose3/resources/text/stopwords-it.txt
goose3/resources/text/stopwords-ja.txt
goose3/resources/text/stopwords-ko.txt
goose3/resources/text/stopwords-lt.txt
goose3/resources/text/stopwords-mk.txt
goose3/resources/text/stopwords-nb.txt
goose3/resources/text/stopwords-nl.txt
goose3/resources/text/stopwords-no.txt
goose3/resources/text/stopwords-pl.txt
goose3/resources/text/stopwords-pt.txt
goose3/resources/text/stopwords-ro.txt
goose3/resources/text/stopwords-ru.txt
goose3/resources/text/stopwords-sl.txt
goose3/resources/text/stopwords-sr.txt
goose3/resources/text/stopwords-sv.txt
goose3/resources/text/stopwords-sw.txt
goose3-3.1.20.dist-info/licenses/LICENSE.txt
goose3-3.1.20.dist-info/METADATA
goose3-3.1.20.dist-info/WHEEL
goose3-3.1.20.dist-info/top_level.txt
goose3-3.1.20.dist-info/RECORD
