Metadata-Version: 2.4
Name: goose3
Version: 3.1.20
Summary: Html Content / Article Extractor, web scrapping for Python3
Home-page: https://github.com/goose3/goose3
Author: Mahmoud Lababidi
Author-email: lababidi+py@gmail.com
License: Apache
Keywords: python,scrapping,extractor,web scrapping,nlp
Classifier: Development Status :: 4 - Beta
Classifier: Environment :: Other Environment
Classifier: Intended Audience :: Developers
Classifier: License :: OSI Approved :: Apache Software License
Classifier: Operating System :: MacOS :: MacOS X
Classifier: Operating System :: POSIX
Classifier: Operating System :: Microsoft :: Windows
Classifier: Programming Language :: Python
Classifier: Programming Language :: Python :: 3
Classifier: Programming Language :: Python :: 3.9
Classifier: Programming Language :: Python :: 3.10
Classifier: Programming Language :: Python :: 3.11
Classifier: Programming Language :: Python :: 3.12
Classifier: Programming Language :: Python :: 3.13
Classifier: Topic :: Internet
Classifier: Topic :: Utilities
Classifier: Topic :: Software Development :: Libraries :: Python Modules
Requires-Python: >=3.9
License-File: LICENSE.txt
Requires-Dist: requests
Requires-Dist: Pillow
Requires-Dist: lxml
Requires-Dist: cssselect
Requires-Dist: beautifulsoup4
Requires-Dist: python-dateutil
Requires-Dist: langdetect
Requires-Dist: pyahocorasick
Provides-Extra: chinese
Requires-Dist: jieba; extra == "chinese"
Provides-Extra: arabic
Requires-Dist: nltk; extra == "arabic"
Provides-Extra: japanese
Requires-Dist: fugashi[unidic-lite]; extra == "japanese"
Provides-Extra: all
Requires-Dist: jieba; extra == "all"
Requires-Dist: nltk; extra == "all"
Requires-Dist: fugashi[unidic-lite]; extra == "all"
Dynamic: license-file
